README.rst
setup.py
intensional/__init__.py
intensional/contenthash.py
intensional/core.py
intensional.egg-info/PKG-INFO
intensional.egg-info/SOURCES.txt
intensional.egg-info/dependency_links.txt
intensional.egg-info/requires.txt
intensional.egg-info/top_level.txt
intensional.egg-info/zip-safe
test/test.py