Metadata-Version: 1.0
Name: intensional
Version: 0.220
Summary: Intensional sets in Python
Home-page: https://bitbucket.org/jeunice/intensional
Author: Jonathan Eunice
Author-email: jonathan.eunice@gmail.com
License: UNKNOWN
Keywords: intensional sets lambda expression list comprehension
Platform: UNKNOWN
Classifier: Development Status :: 3 - Alpha
Classifier: Operating System :: OS Independent
Classifier: License :: OSI Approved :: BSD License
Classifier: Intended Audience :: Developers
Classifier: Programming Language :: Python
Classifier: Programming Language :: Python :: 2.5
Classifier: Programming Language :: Python :: 2.6
Classifier: Programming Language :: Python :: 2.7
Classifier: Programming Language :: Python :: 3.2
Classifier: Programming Language :: Python :: 3.3
Classifier: Programming Language :: Python :: Implementation :: CPython
Classifier: Programming Language :: Python :: Implementation :: PyPy
Classifier: Topic :: Software Development :: Libraries :: Python Modules
